{
    "ENABLE_TWO_FACTOR_AUTHENTICATION": 0,
    "EXCLUDE_SYSTEM_ADMINISTRATOR_FROM_LOCKOUT": false,
    "MAX_INVALID_LOGIN_ATTEMPTS": 0,
    "PASSWORD_BLACKLIST": "",
    "PASSWORD_ENABLE_AGING": false,
    "PASSWORD_FORCE_COMPLEX": 0,
    "PASSWORD_HISTORY_SIZE": 0,
    "PASSWORD_MAXIMUM_AGE": "P90D",
    "PASSWORD_MINIMUM_LENGTH": 1,
    "USERS": {
        "__SystemAdministrator": {
            "ALGORITHM": 1,
            "ENABLED": true,
            "LAST_PASSWORD_CHANGE": "2026-03-09T12:07:36.678766Z",
            "PASSWORD": "fa60fc5a9f49ed0be9d05a05aeecddf091f5e60cadcaefae188664ea240c5999486c6ed6bc8ceabedbc03caa637897876625439abc03c0ef2a1dc9ff8bb58f2c",
            "PASSWORD_HISTORY": [],
            "SALT": "5SjaxzEv0e9OPJ8LEq/kPm5IaerE+TLG9wqYUNru8QyGs5i37x3SP33YbdjJUdCIJtg63t356qypk3juzGKrHQ==",
            "SECRET": {
                "algorithm": 0,
                "configuration": 0,
                "iv": "",
                "value": ""
            },
            "TWO_FACTOR_AUTHENTICATION_ENABLED": false
        },
        "__SystemGuest": {
            "ALGORITHM": 0,
            "ENABLED": true,
            "LAST_PASSWORD_CHANGE": "1970-01-01T00:00:00Z",
            "PASSWORD": "",
            "PASSWORD_HISTORY": [],
            "SALT": "",
            "SECRET": {
                "algorithm": 0,
                "configuration": 0,
                "iv": "",
                "value": ""
            },
            "TWO_FACTOR_AUTHENTICATION_ENABLED": false
        },
        "__SystemUser": {
            "ALGORITHM": 0,
            "ENABLED": true,
            "LAST_PASSWORD_CHANGE": "1970-01-01T00:00:00Z",
            "PASSWORD": "",
            "PASSWORD_HISTORY": [],
            "SALT": "",
            "SECRET": {
                "algorithm": 0,
                "configuration": 0,
                "iv": "",
                "value": ""
            },
            "TWO_FACTOR_AUTHENTICATION_ENABLED": false
        }
    }
}