{
  "function": {
    "name": "slideCarrousel",
    "namespace": "TcHmi.Functions.PrHmi_Animaciones",
    "displayName": "slideCarrousel",
    "description": "",
    "waitMode": "Synchronous",
    "category": "Animation",
    "returnValue": {
      "type": "tchmi:general#/definitions/String"
    },
    "visible": true,
    "injectContextObject": false,
    "arguments": [
      {
        "name": "idContent",
        "displayName": "idContent",
        "type": "tchmi:general#/definitions/String",
        "description": "id content inside frame",
        "defaultValue": null,
        "required": true,
        "bindable": true,
        "restParameter": false,
        "asReference": false,
        "allowControlAttributeBindingOptions": false
      },
      {
        "name": "frame",
        "displayName": "frame",
        "type": "tchmi:general#/definitions/Number",
        "description": "frame width",
        "defaultValue": null,
        "required": true,
        "bindable": true,
        "restParameter": false,
        "asReference": false,
        "allowControlAttributeBindingOptions": false
      },
      {
        "name": "step",
        "displayName": "step",
        "type": "tchmi:general#/definitions/Number",
        "description": "step feed",
        "defaultValue": null,
        "required": true,
        "bindable": true,
        "restParameter": false,
        "asReference": false,
        "allowControlAttributeBindingOptions": false
      }
    ]
  },
  "$schema": "./../../Packages/Beckhoff.TwinCAT.HMI.Framework.14.3.431/runtimes/native1.12-tchmi/Schema/FunctionDescription.Schema.json",
  "apiVersion": 1,
  "version": {
    "full": "0.0.0.0",
    "major": 0,
    "minor": 0,
    "revision": 0,
    "build": 0
  },
  "dependencyFiles": [
    {
      "name": "slideContent.js",
      "type": "JavaScript",
      "description": ""
    }
  ]
}